rqdatac_esg/__init__.py
rqdatac_esg/_version.py
rqdatac_esg/api.py
rqdatac_esg/utils.py
rqdatac_esg-0.1.3.dist-info/METADATA
rqdatac_esg-0.1.3.dist-info/WHEEL
rqdatac_esg-0.1.3.dist-info/top_level.txt
rqdatac_esg-0.1.3.dist-info/RECORD
